rtl/mux4to1.sv
module mux4to1 #(
    parameter WIDTH = 8
) (
    input  logic [WIDTH-1:0] in0,
    input  logic [WIDTH-1:0] in1,
    input  logic [WIDTH-1:0] in2,
    input  logic [WIDTH-1:0] in3,
    input  logic [1:0]       sel,
    output logic [WIDTH-1:0] out
);

    always_comb begin
        case (sel)
            2'b00: out = in0;
            2'b01: out = in1;
            2'b10: out = in2;
            2'b11: out = in3;
            default: out = '0;
        endcase
    end

endmodule

sim/tb_mux4to1/tb_mux4to1.sv
`timescale 1ns/1ps

module tb_mux4to1;

    parameter WIDTH = 8;
    
    logic [WIDTH-1:0] in0, in1, in2, in3;
    logic [1:0] sel;
    logic [WIDTH-1:0] out;
    
    // Instantiate DUT
    mux4to1 #(.WIDTH(WIDTH)) dut (
        .in0(in0),
        .in1(in1),
        .in2(in2),
        .in3(in3),
        .sel(sel),
        .out(out)
    );
    
    // Test procedure
    initial begin
        $display("Starting MUX 4:1 Test");
        $display("Time\tsel\tin0\tin1\tin2\tin3\tout");
        
        // Initialize inputs
        in0 = 8'hAA;
        in1 = 8'hBB;
        in2 = 8'hCC;
        in3 = 8'hDD;
        
        // Test all select combinations
        for (int i = 0; i < 4; i++) begin
            sel = i[1:0];
            #10;
            $display("%0t\t%b\t%h\t%h\t%h\t%h\t%h", 
                     $time, sel, in0, in1, in2, in3, out);
            
            // Check correctness
            case (sel)
                2'b00: assert(out == in0) else $error("Mismatch for sel=00");
                2'b01: assert(out == in1) else $error("Mismatch for sel=01");
                2'b10: assert(out == in2) else $error("Mismatch for sel=10");
                2'b11: assert(out == in3) else $error("Mismatch for sel=11");
            endcase
        end
        
        // Test with different input values
        in0 = 8'h11; in1 = 8'h22; in2 = 8'h33; in3 = 8'h44;
        #10;
        
        for (int i = 0; i < 4; i++) begin
            sel = i[1:0];
            #10;
            $display("%0t\t%b\t%h\t%h\t%h\t%h\t%h", 
                     $time, sel, in0, in1, in2, in3, out);
        end
        
        $display("Test Complete");
        $finish;
    end
    
    initial begin 
        $dumpfile("tb_mux4to1.vcd");  
        $dumpvars(0, tb_mux4to1); 
    end

endmodule

sim/tb_mux4to1/tb_mux4to1.vcd
$version Generated by VerilatedVcd $end
$timescale 1ps $end
 $scope module $rootio $end
 $upscope $end
 $scope module tb_mux4to1 $end
  $var wire 32 + WIDTH [31:0] $end
  $var wire 8 # in0 [7:0] $end
  $var wire 8 $ in1 [7:0] $end
  $var wire 8 % in2 [7:0] $end
  $var wire 8 & in3 [7:0] $end
  $var wire 2 ' sel [1:0] $end
  $var wire 8 ( out [7:0] $end
  $scope module dut $end
   $var wire 32 + WIDTH [31:0] $end
   $var wire 8 # in0 [7:0] $end
   $var wire 8 $ in1 [7:0] $end
   $var wire 8 % in2 [7:0] $end
   $var wire 8 & in3 [7:0] $end
   $var wire 2 ' sel [1:0] $end
   $var wire 8 ( out [7:0] $end
  $upscope $end
  $scope module unnamedblk1 $end
   $var wire 32 ) i [31:0] $end
  $upscope $end
  $scope module unnamedblk2 $end
   $var wire 32 * i [31:0] $end
  $upscope $end
 $upscope $end
$enddefinitions $end


#0
b10101010 #
b10111011 $
b11001100 %
b11011101 &
b00 '
b10101010 (
b00000000000000000000000000000000 )
b00000000000000000000000000000000 *
b00000000000000000000000000001000 +
#10000
b01 '
b10111011 (
b00000000000000000000000000000001 )
#20000
b10 '
b11001100 (
b00000000000000000000000000000010 )
#30000
b11 '
b11011101 (
b00000000000000000000000000000011 )
#40000
b00010001 #
b00100010 $
b00110011 %
b01000100 &
b01000100 (
b00000000000000000000000000000100 )
#50000
b00 '
b00010001 (
#60000
b01 '
b00100010 (
b00000000000000000000000000000001 *
#70000
b10 '
b00110011 (
b00000000000000000000000000000010 *
#80000
b11 '
b01000100 (
b00000000000000000000000000000011 *
#90000
b00000000000000000000000000000100 *
